deepview/__init__.py
deepview/_availability.py
deepview/_dict_utils.py
deepview/_logging.py
deepview/base/__init__.py
deepview/base/_cached_producer.py
deepview/base/_image_producer.py
deepview/base/_introspector.py
deepview/base/_model.py
deepview/base/_multi_introspect.py
deepview/base/_pipeline.py
deepview/base/_producer.py
deepview/base/_response_info.py
deepview/base/_traintest_producer.py
deepview/base/_batch/__init__.py
deepview/base/_batch/_batch.py
deepview/base/_batch/_fields.py
deepview/base/_batch/_metadata_storage.py
deepview/base/_batch/_storage.py
deepview/exceptions/__init__.py
deepview/exceptions/_deepview_exceptions.py
deepview/introspectors/__init__.py
deepview/introspectors/_duplicates.py
deepview/introspectors/_dim_reduction/__init__.py
deepview/introspectors/_dim_reduction/_dimension_reduction.py
deepview/introspectors/_dim_reduction/_protocols.py
deepview/introspectors/_dim_reduction/_reducers.py
deepview/introspectors/_familiarity/__init__.py
deepview/introspectors/_familiarity/_familiarity.py
deepview/introspectors/_familiarity/_gaussian_familiarity.py
deepview/introspectors/_familiarity/_gmm_familiarity.py
deepview/introspectors/_familiarity/_protocols.py
deepview/introspectors/_iua/__init__.py
deepview/introspectors/_iua/_iua.py
deepview/introspectors/_pfa/__init__.py
deepview/introspectors/_pfa/_covariances_calculator.py
deepview/introspectors/_pfa/_pfa.py
deepview/introspectors/_pfa/_pfa_algorithms.py
deepview/introspectors/_pfa/_pfa_units.py
deepview/introspectors/_pfa/_recommendation.py
deepview/introspectors/_report/__init__.py
deepview/introspectors/_report/_dataframe_formatting.py
deepview/introspectors/_report/_dataset_report.py
deepview/introspectors/_report/_dataset_report_stages.py
deepview/introspectors/_report/_familiarity_wrappers.py
deepview/introspectors/_report/_report_builder_introspectors.py
deepview/introspectors/_report/_string_util.py
deepview/processors/__init__.py
deepview/processors/_base_processor.py
deepview-3.9.6.dist-info/WHEEL
deepview-3.9.6.dist-info/METADATA
deepview-3.9.6.dist-info/RECORD
